{"metadata":{"title":"Lorem no ips","displayTitle":null,"cover":{"url":"https://www.storytel.se/images/customList/18.jpg","height":350,"width":640},"description":"Lorem no ipsum lorem rebum ut praesent tempor laoreet magna vel est feugait et labore takimata et elitr dolores duo eos aliquyam labore et soluta dolor commodo amet duis amet in labore qui dolor et nulla et facilisis est duo elitr euismod duis no amet amet gube","logo":{"url":"https://www.storytel.se/images/customList/14.jpg","height":350,"width":640},"followUrl":"/consumables/list/1/follow"},"userSpecific":null,"consumables":[{"metadata":{"id":"6","title":"Everything I Know About Women I Learned From My Tractor","type":"episodic","cover":{"url":"https://www.storytel.se/e/images/640x640/305.jpg","height":640,"width":413},"authors":[{"id":"5","name":"Philip J. Fry"},{"id":"4","name":"Bender Bending Rodríguez"}],"narrators":[{"id":"4","name":"Bender Bending Rodríguez"},{"id":"2","name":"Amy Wong"}],"formats":[{"id":"1","type":"audio","releaseDate":"2016-05-20T00:00:00.0000000+00:00","isReleased":false,"length":null},{"id":"1","type":"audio","releaseDate":"2016-11-04T00:00:00.0000000+00:00","isReleased":false,"length":null},{"id":"1","type":"audio","releaseDate":"2016-11-04T00:00:00.0000000+00:00","isReleased":false,"length":null},{"id":"1","type":"audio","releaseDate":"2016-11-04T00:00:00.0000000+00:00","isReleased":false,"length":null}]},"userSpecific":null},{"metadata":{"id":"1","title":"Reusing Old Graves","type":"single","cover":{"url":"https://www.storytel.se/e/images/640x640/124.jpg","height":640,"width":415},"authors":[{"id":"1","name":"Hermes Conrad"},{"id":"2","name":"Amy Wong"},{"id":"3","name":"John A. Zoidberg"}],"narrators":[{"id":"3","name":"Turanga Leela"},{"id":"2","name":"Amy Wong"},{"id":"4","name":"Bender Bending Rodríguez"}],"formats":[{"id":"1","type":"audio","releaseDate":"2016-05-20T00:00:00.0000000+00:00","isReleased":false,"length":null},{"id":"2","type":"epub","releaseDate":"2016-04-20T00:00:00.0000000+00:00","isReleased":false,"length":null}]},"userSpecific":null},{"metadata":{"id":"8","title":"Eating People is Wrong","type":"episodic","cover":{"url":"https://www.storytel.se/images/e/640x640/307.jpg","height":640,"width":413},"authors":[{"id":"5","name":"Philip J. Fry"},{"id":"3","name":"Turanga Leela"},{"id":"4","name":"Bender Bending Rodríguez"}],"narrators":[{"id":"3","name":"John A. Zoidberg"}],"formats":[{"id":"1","type":"audio","releaseDate":"2016-05-20T00:00:00.0000000+00:00","isReleased":false,"length":null}]},"userSpecific":null},{"metadata":{"id":"5","title":"The Manly Art of Knitting","type":"episodic","cover":{"url":"https://www.storytel.se/images/640x640/290.jpg","height":640,"width":640},"authors":[{"id":"5","name":"Philip J. Fry"},{"id":"6","name":"Hubert J. Farnsworth"}],"narrators":[{"id":"5","name":"Philip J. Fry"},{"id":"2","name":"Amy Wong"},{"id":"6","name":"Hubert J. Farnsworth"}],"formats":[{"id":"1","type":"audio","releaseDate":"2016-05-20T00:00:00.0000000+00:00","isReleased":false,"length":null}]},"userSpecific":null},{"metadata":{"id":"2","title":"Why Cats Paint","type":"episodic","cover":{"url":"https://www.storytel.se/images/e/640x640/256.jpg","height":640,"width":480},"authors":[{"id":"4","name":"Bender Bending Rodríguez"},{"id":"3","name":"John A. Zoidberg"},{"id":"1","name":"Hermes Conrad"}],"narrators":[{"id":"5","name":"Philip J. Fry"},{"id":"4","name":"Bender Bending Rodríguez"},{"id":"3","name":"Turanga Leela"}],"formats":[{"id":"1","type":"audio","releaseDate":"2016-05-20T00:00:00.0000000+00:00","isReleased":false,"length":null},{"id":"1","type":"audio","releaseDate":"2016-09-13T00:00:00.0000000+00:00","isReleased":false,"length":null}]},"userSpecific":null},{"metadata":{"id":"4","title":"How To Raise Your IQ By Eating Gifted Children","type":"single","cover":{"url":"https://www.storytel.se/images/e/640x640/2048.jpg","height":640,"width":412},"authors":[{"id":"4","name":"Bender Bending Rodríguez"},{"id":"2","name":"Amy Wong"}],"narrators":[{"id":"3","name":"Turanga Leela"},{"id":"6","name":"Hubert J. Farnsworth"}],"formats":[{"id":"1","type":"epub","releaseDate":"2016-05-20T00:00:00.0000000+00:00","isReleased":false,"length":null}]},"userSpecific":null},{"metadata":{"id":"7","title":"Everything I Want To Do Is Illegal","type":"single","cover":{"url":"https://www.storytel.se/images/640x640/306.jpg","height":640,"width":406},"authors":[{"id":"2","name":"Amy Wong"},{"id":"6","name":"Hubert J. Farnsworth"}],"narrators":[{"id":"1","name":"Hermes Conrad"},{"id":"3","name":"Turanga Leela"}],"formats":[{"id":"1","type":"audio","releaseDate":"2016-05-20T00:00:00.0000000+00:00","isReleased":false,"length":null}]},"userSpecific":null},{"metadata":{"id":"3","title":"Mommy Drinks Because You're Bad","type":"single","cover":{"url":"https://www.storytel.se/images/640x640/1024.jpg","height":640,"width":640},"authors":[{"id":"2","name":"Amy Wong"}],"narrators":[{"id":"1","name":"Hermes Conrad"}],"formats":[{"id":"1","type":"epub","releaseDate":"2013-01-25T00:00:00.0000000+00:00","isReleased":false,"length":null}]},"userSpecific":null}],"nextPage":"a0c907701bb9482d9878b19d0d3fcb78"}
